asppackage/__init__.py
asppackage/functions.py
asppackage/greet.py
ajayspackage-0.0.1.dist-info/LICENCE.txt
ajayspackage-0.0.1.dist-info/METADATA
ajayspackage-0.0.1.dist-info/WHEEL
ajayspackage-0.0.1.dist-info/top_level.txt
ajayspackage-0.0.1.dist-info/RECORD
